{
  "tw": {
    "updated_at": "2026-07-12 09:59",
    "date": "2026-07-12",
    "market_note": "台股AI與半導體題材續熱，主動式ETF受關注。權值股法說會前夕觀望，留意籌碼變化。",
    "items": [
      {
        "code": "00403A",
        "name": "主動統一升級50",
        "action": "續抱",
        "qty": "",
        "price": "",
        "stop": "",
        "reason": "募集高、爆量已反映，待經理人績效與11月首次配息。",
        "price_now": "10.48",
        "market": "TW"
      },
      {
        "code": "0050",
        "name": "元大台灣50",
        "action": "續抱",
        "qty": "",
        "price": "",
        "stop": "",
        "reason": "追蹤大盤被動式ETF，無短期買賣訊號，核心邏輯未變。",
        "price_now": "105.80",
        "market": "TW"
      },
      {
        "code": "2303",
        "name": "聯電",
        "action": "續抱",
        "qty": "",
        "price": "",
        "stop": "",
        "reason": "營收成長，12奈米、矽中介層與漲價題材仍在，外資買超。",
        "price_now": "156.00",
        "market": "TW"
      },
      {
        "code": "2308",
        "name": "台達電",
        "action": "續抱",
        "qty": "",
        "price": "",
        "stop": "",
        "reason": "營收創高，AI伺服器電源與液冷散熱下半年將放量。",
        "price_now": "1,880.00",
        "market": "TW"
      },
      {
        "code": "2313",
        "name": "華通",
        "action": "續抱",
        "qty": "",
        "price": "",
        "stop": "",
        "reason": "營收創高，低軌衛星與AI伺服器需求強勁，持續擴產。",
        "price_now": "223.00",
        "market": "TW"
      },
      {
        "code": "2330",
        "name": "台積電",
        "action": "觀望",
        "qty": "",
        "price": "",
        "stop": "",
        "reason": "等待7/16法說會對下半年展望，外資近期有賣超。",
        "price_now": "2,415.00",
        "market": "TW"
      },
      {
        "code": "2454",
        "name": "聯發科",
        "action": "續抱",
        "qty": "",
        "price": "",
        "stop": "",
        "reason": "6月營收與Q2業績超財測，AI ASIC與旗艦晶片題材強勁。",
        "price_now": "3,925.00",
        "market": "TW"
      },
      {
        "code": "2867",
        "name": "三商壽",
        "action": "觀察",
        "qty": "",
        "price": "",
        "stop": "",
        "reason": "無近期營運或政策消息，需等待明確訊號。",
        "price_now": "8.86",
        "market": "TW"
      },
      {
        "code": "6669",
        "name": "緯穎",
        "action": "續抱",
        "qty": "",
        "price": "",
        "stop": "",
        "reason": "營收創高，AI伺服器與ASIC下半年新品量產可期。",
        "price_now": "5,040.00",
        "market": "TW"
      },
      {
        "code": "5274",
        "name": "信驊",
        "action": "續抱",
        "qty": "",
        "price": "",
        "stop": "",
        "reason": "營收創高，BMC需求強勁，輝達新平台與AST2700放量可期。",
        "price_now": "13,665.00",
        "market": "TW"
      }
    ]
  },
  "us": {
    "updated_at": "2026-07-11 22:01",
    "date": "2026-07-11",
    "market_note": "AI題材續強，精選有未定價催化劑個股，留意內部人賣壓。",
    "items": [
      {
        "code": "GOOGL",
        "name": "Alphabet",
        "action": "加碼",
        "qty": "5股",
        "price": "358.00",
        "stop": "345.00",
        "reason": "AI與雲端業務強勁成長，分析師目標價高，股價具上漲潛力。",
        "price_now": "357.18",
        "market": "US"
      },
      {
        "code": "NVDA",
        "name": "輝達 NVDA",
        "action": "加碼",
        "qty": "10股",
        "price": "212.50",
        "stop": "205.00",
        "reason": "中國H200需求潛力、800億回購、分析師看漲與低估值。",
        "price_now": "210.96",
        "market": "US"
      },
      {
        "code": "SPCX",
        "name": "太空探索 SpaceX",
        "action": "加碼",
        "qty": "10股",
        "price": "146.00",
        "stop": "135.00",
        "reason": "納斯達克100指數納入引發被動買盤，AI合約強勁。",
        "price_now": "145.30",
        "market": "US"
      },
      {
        "code": "TSM",
        "name": "台積電ADR",
        "action": "加碼",
        "qty": "5股",
        "price": "435.00",
        "stop": "420.00",
        "reason": "7/16分析師會議預期上調財測與資本支出，AI需求強勁。",
        "price_now": "434.11",
        "market": "US"
      }
    ]
  }
}